diminuendo/__init__.py
diminuendo/htmlmin.py
python_diminuendo-0.1.1.dist-info/WHEEL
python_diminuendo-0.1.1.dist-info/metadata.json
python_diminuendo-0.1.1.dist-info/DESCRIPTION.rst
python_diminuendo-0.1.1.dist-info/top_level.txt
python_diminuendo-0.1.1.dist-info/RECORD
python_diminuendo-0.1.1.dist-info/METADATA
