Metadata-Version: 2.0
Name: python-diminuendo
Version: 0.1.1
Summary: A generic HTML minifier for python
Home-page: https://github.com/hrbonz/python-diminuendo
Author: Stefan "hr" Berder
Author-email: hr@bonz.org
License: BSD 3-Clause
Keywords: minify html
Platform: UNKNOWN
Classifier: Development Status :: 3 - Alpha
Classifier: Environment :: Console
Classifier: Intended Audience :: Developers
Classifier: License :: OSI Approved :: BSD License
Classifier: Programming Language :: Python :: 2.7
Classifier: Programming Language :: Python :: 3.3
Classifier: Topic :: Internet
Requires-Dist: beautifulsoup4
Requires-Dist: html5lib
